cpp_aws_s3_pdf/__init__.py
cpp_aws_s3_pdf/exceptions.py
cpp_aws_s3_pdf/s3_pdf.py
cpp_aws_s3_pdf/utils/__init__.py
cpp_aws_s3_pdf/utils/aws_s3.py
cpp_aws_s3_pdf/utils/image.py
cpp_aws_s3_pdf/utils/pdf.py
cpp_aws_s3_pdf-1.1.1.dist-info/METADATA
cpp_aws_s3_pdf-1.1.1.dist-info/WHEEL
cpp_aws_s3_pdf-1.1.1.dist-info/licenses/LICENSE
cpp_aws_s3_pdf-1.1.1.dist-info/RECORD
