Metadata-Version: 2.1
Name: cpp_aws_s3_pdf
Version: 1.1.1
Summary: This package createds a PDF file from selected s3 objects
Project-URL: Homepage, https://github.com/noble-cc/cpp_aws_s3_pdf
Project-URL: Issues, https://github.com/noble-cc/cpp_aws_s3_pdf/issues
Author-email: Noble Obioma <nobioma1@gmail.com>
License-File: LICENSE
Classifier: License :: OSI Approved :: MIT License
Classifier: Operating System :: OS Independent
Classifier: Programming Language :: Python :: 3
Requires-Python: >=3.8
Requires-Dist: boto3>=1.28.76
Requires-Dist: botocore>=1.31.76
Requires-Dist: pillow>=10.1.0
Requires-Dist: pypdf>=3.17.1
